sqlite_dbm.py
sqlite_dbm-3.2.1.dist-info/METADATA
sqlite_dbm-3.2.1.dist-info/WHEEL
sqlite_dbm-3.2.1.dist-info/top_level.txt
sqlite_dbm-3.2.1.dist-info/RECORD
