Metadata-Version: 2.1
Name: sqlite-dbm
Version: 3.2.1
Summary: Dict-style DBM based on sqlite3.
Home-page: https://github.com/imbolc/sqlite_dbm
Author: Imbolc
Author-email: imbolc@imbolc.name
License: ISC
Classifier: Development Status :: 4 - Beta
Classifier: Intended Audience :: Developers
Classifier: License :: OSI Approved :: ISC License (ISCL)
Classifier: Programming Language :: Python
Classifier: Programming Language :: Python :: 3
